[{"date": "2025-04-13", "units": 388, "amount": 2218, "paid": true, "payment_delay_days": 0}, {"date": "2025-05-13", "units": 231, "amount": 1034, "paid": true, "payment_delay_days": 0}, {"date": "2025-06-12", "units": 227, "amount": 736, "paid": true, "payment_delay_days": 0}, {"date": "2025-07-12", "units": 242, "amount": 1396, "paid": true, "payment_delay_days": 0}, {"date": "2025-08-11", "units": 278, "amount": 1288, "paid": true, "payment_delay_days": 0}, {"date": "2025-09-10", "units": 360, "amount": 1791, "paid": true, "payment_delay_days": 0}]