[{"date": "2025-03-14", "units": 229, "amount": 883, "paid": false, "payment_delay_days": 32}, {"date": "2025-04-13", "units": 86, "amount": 321, "paid": true, "payment_delay_days": 0}, {"date": "2025-05-13", "units": 411, "amount": 2249, "paid": true, "payment_delay_days": 0}, {"date": "2025-06-12", "units": 405, "amount": 1722, "paid": true, "payment_delay_days": 0}, {"date": "2025-07-12", "units": 229, "amount": 1360, "paid": false, "payment_delay_days": 27}, {"date": "2025-08-11", "units": 210, "amount": 1005, "paid": true, "payment_delay_days": 0}, {"date": "2025-09-10", "units": 183, "amount": 861, "paid": true, "payment_delay_days": 0}]